{
  "main": {
    "id": "694aeef79a72c2e3",
    "type": "split",
    "children": [
      {
        "id": "f489d907ad8c34f5",
        "type": "tabs",
        "children": [
          {
            "id": "0058d221f652ef50",
            "type": "leaf",
            "state": {
              "type": "markdown",
              "state": {
                "file": "README.md",
                "mode": "source",
                "source": false
              }
            }
          },
          {
            "id": "46c9ccb229d2a533",
            "type": "leaf",
            "state": {
              "type": "markdown",
              "state": {
                "file": "ddd.md",
                "mode": "source",
                "source": false
              }
            }
          }
        ],
        "currentTab": 1
      }
    ],
    "direction": "vertical"
  },
  "left": {
    "id": "49136346d4163752",
    "type": "split",
    "children": [
      {
        "id": "fd533cfaab0dc2cf",
        "type": "tabs",
        "children": [
          {
            "id": "1daba2496e8f76d3",
            "type": "leaf",
            "state": {
              "type": "file-explorer",
              "state": {
                "sortOrder": "alphabetical"
              }
            }
          },
          {
            "id": "2d1df7055b22974f",
            "type": "leaf",
            "state": {
              "type": "search",
              "state": {
                "query": "",
                "matchingCase": false,
                "explainSearch": false,
                "collapseAll": false,
                "extraContext": false,
                "sortOrder": "alphabetical"
              }
            }
          },
          {
            "id": "8a6fac2ca6fb8a9c",
            "type": "leaf",
            "state": {
              "type": "bookmarks",
              "state": {}
            }
          }
        ]
      }
    ],
    "direction": "horizontal",
    "width": 300
  },
  "right": {
    "id": "660aa2fdd99b75fc",
    "type": "split",
    "children": [
      {
        "id": "1eae8ec0106b3de3",
        "type": "tabs",
        "children": [
          {
            "id": "d0eb9b76336df092",
            "type": "leaf",
            "state": {
              "type": "backlink",
              "state": {
                "file": "ddd.md",
                "collapseAll": false,
                "extraContext": false,
                "sortOrder": "alphabetical",
                "showSearch": false,
                "searchQuery": "",
                "backlinkCollapsed": false,
                "unlinkedCollapsed": true
              }
            }
          },
          {
            "id": "a0615de5ed4b9c85",
            "type": "leaf",
            "state": {
              "type": "outgoing-link",
              "state": {
                "file": "ddd.md",
                "linksCollapsed": false,
                "unlinkedCollapsed": true
              }
            }
          },
          {
            "id": "6f9603d48317c031",
            "type": "leaf",
            "state": {
              "type": "tag",
              "state": {
                "sortOrder": "frequency",
                "useHierarchy": true
              }
            }
          },
          {
            "id": "8c5cb289f4ca3242",
            "type": "leaf",
            "state": {
              "type": "outline",
              "state": {
                "file": "ddd.md"
              }
            }
          }
        ]
      }
    ],
    "direction": "horizontal",
    "width": 300,
    "collapsed": true
  },
  "left-ribbon": {
    "hiddenItems": {
      "switcher:打开快速切换": false,
      "graph:查看关系图谱": false,
      "canvas:新建白板": false,
      "daily-notes:打开/创建今天的日记": false,
      "templates:插入模板": false,
      "command-palette:打开命令面板": false
    }
  },
  "active": "46c9ccb229d2a533",
  "lastOpenFiles": [
    "README.md",
    "ddd.md"
  ]
}